{
	"backtrace" : 0,
	"backtraceGraph" : 
	{
		"commands" : [],
		"files" : 
		[
			"src/Vahid/CMakeLists.txt"
		],
		"nodes" : 
		[
			{
				"file" : 0
			}
		]
	},
	"dependencies" : 
	[
		{
			"id" : "Vahid_autogen_timestamp_deps::@c435647b630cea22cbd7"
		}
	],
	"folder" : 
	{
		"name" : "QtInternalTargets"
	},
	"id" : "Vahid_autogen::@c435647b630cea22cbd7",
	"isGeneratorProvided" : true,
	"name" : "Vahid_autogen",
	"paths" : 
	{
		"build" : "src/Vahid",
		"source" : "src/Vahid"
	},
	"sourceGroups" : 
	[
		{
			"name" : "",
			"sourceIndexes" : 
			[
				0
			]
		},
		{
			"name" : "CMake Rules",
			"sourceIndexes" : 
			[
				1,
				2
			]
		}
	],
	"sources" : 
	[
		{
			"backtrace" : 0,
			"isGenerated" : true,
			"path" : "build/Desktop_Qt_6_6_3_MSVC2019_64bit-Debug/src/Vahid/CMakeFiles/Vahid_autogen",
			"sourceGroupIndex" : 0
		},
		{
			"backtrace" : 0,
			"isGenerated" : true,
			"path" : "build/Desktop_Qt_6_6_3_MSVC2019_64bit-Debug/src/Vahid/CMakeFiles/Vahid_autogen.rule",
			"sourceGroupIndex" : 1
		},
		{
			"backtrace" : 0,
			"isGenerated" : true,
			"path" : "build/Desktop_Qt_6_6_3_MSVC2019_64bit-Debug/src/Vahid/Vahid_autogen/timestamp.rule",
			"sourceGroupIndex" : 1
		}
	],
	"type" : "UTILITY"
}
